{"success": true, "results": [{"date": "2021-06-13", "name": "Alabama", "id": "USA_US-AL", "total_count": 1, "lineage_count": 0, "cum_total_count": 166, "cum_lineage_count": 1, "proportion": 0.006024096385542169, "proportion_ci_lower": 0.0006507556157824076, "proportion_ci_upper": 0.02780654442039998}, {"date": "2021-06-13", "name": "Alaska", "id": "USA_US-AK", "total_count": 6, "lineage_count": 0, "cum_total_count": 657, "cum_lineage_count": 8, "proportion": 0.0121765601217656, "proportion_ci_lower": 0.005772984903051078, "proportion_ci_upper": 0.02284376608643457}, {"date": "2021-06-23", "name": "Arizona", "id": "USA_US-AZ", "total_count": 2, "lineage_count": 0, "cum_total_count": 1209, "cum_lineage_count": 10, "proportion": 0.008271298593879239, "proportion_ci_lower": 0.004260338174494931, "proportion_ci_upper": 0.014622843717594147}, {"date": "2021-06-10", "name": "Arkansas", "id": "USA_US-AR", "total_count": 2, "lineage_count": 0, "cum_total_count": 203, "cum_lineage_count": 0, "proportion": 0.0, "proportion_ci_lower": 2.4159094409331092e-06, "proportion_ci_upper": 0.012282801560070312}, {"date": "2021-06-16", "name": "California", "id": "USA_US-CA", "total_count": 1, "lineage_count": 0, "cum_total_count": 4709, "cum_lineage_count": 89, "proportion": 0.018899978764068806, "proportion_ci_lower": 0.015300439272290356, "proportion_ci_upper": 0.02309042051535337}, {"date": "2021-06-15", "name": "Colorado", "id": "USA_US-CO", "total_count": 1, "lineage_count": 0, "cum_total_count": 4727, "cum_lineage_count": 55, "proportion": 0.011635286651152951, "proportion_ci_lower": 0.008868982097764704, "proportion_ci_upper": 0.014998938243586113}, {"date": "2021-06-23", "name": "Connecticut", "id": "USA_US-CT", "total_count": 1, "lineage_count": 0, "cum_total_count": 907, "cum_lineage_count": 1, "proportion": 0.0011025358324145535, "proportion_ci_lower": 0.0001189867428945405, "proportion_ci_upper": 0.005141633096707343}, {"date": "2021-06-10", "name": "Delaware", "id": "USA_US-DE", "total_count": 1, "lineage_count": 0, "cum_total_count": 279, "cum_lineage_count": 0, "proportion": 0.0, "proportion_ci_lower": 1.758402614245115e-06, "proportion_ci_upper": 0.00895497353419008}, {"date": "2021-06-15", "name": "District of Columbia", "id": "USA_US-DC", "total_count": 1, "lineage_count": 0, "cum_total_count": 171, "cum_lineage_count": 1, "proportion": 0.005847953216374269, "proportion_ci_lower": 0.0006317057624893325, "proportion_ci_upper": 0.02700338433033822}, {"date": "2021-06-14", "name": "Florida", "id": "USA_US-FL", "total_count": 2, "lineage_count": 0, "cum_total_count": 4265, "cum_lineage_count": 17, "proportion": 0.003985932004689332, "proportion_ci_lower": 0.0024131755817857195, "proportion_ci_upper": 0.006229816543364519}, {"date": "2021-06-12", "name": "Georgia", "id": "USA_US-GA", "total_count": 1, "lineage_count": 0, "cum_total_count": 920, "cum_lineage_count": 2, "proportion": 0.002173913043478261, "proportion_ci_lower": 0.00045201195605639713, "proportion_ci_upper": 0.00695557830819471}, {"date": "2021-06-28", "name": "Hawaii", "id": "USA_US-HI", "total_count": 1, "lineage_count": 0, "cum_total_count": 384, "cum_lineage_count": 40, "proportion": 0.10416666666666667, "proportion_ci_lower": 0.0765911759721652, "proportion_ci_upper": 0.13767922622978146}, {"date": "2021-06-09", "name": "Idaho", "id": "USA_US-ID", "total_count": 2, "lineage_count": 0, "cum_total_count": 201, "cum_lineage_count": 3, "proportion": 0.014925373134328358, "proportion_ci_lower": 0.004221085497651972, "proportion_ci_upper": 0.03929061236085729}, {"date": "2021-06-12", "name": "Illinois", "id": "USA_US-IL", "total_count": 2, "lineage_count": 0, "cum_total_count": 3231, "cum_lineage_count": 8, "proportion": 0.0024760136180748994, "proportion_ci_lower": 0.0011712384946784846, "proportion_ci_upper": 0.004666594134195234}, {"date": "2021-06-24", "name": "Indiana", "id": "USA_US-IN", "total_count": 2, "lineage_count": 0, "cum_total_count": 2195, "cum_lineage_count": 12, "proportion": 0.005466970387243736, "proportion_ci_lower": 0.002991917308918903, "proportion_ci_upper": 0.009240270229494585}, {"date": "2021-06-09", "name": "Iowa", "id": "USA_US-IA", "total_count": 1, "lineage_count": 0, "cum_total_count": 103, "cum_lineage_count": 2, "proportion": 0.019417475728155338, "proportion_ci_lower": 0.004056449902325247, "proportion_ci_upper": 0.060825838084201056}, {"date": "2021-06-25", "name": "Kansas", "id": "USA_US-KS", "total_count": 9, "lineage_count": 0, "cum_total_count": 1094, "cum_lineage_count": 6, "proportion": 0.005484460694698354, "proportion_ci_lower": 0.0022923331435350876, "proportion_ci_upper": 0.011269669916619485}, {"date": "2021-06-11", "name": "Kentucky", "id": "USA_US-KY", "total_count": 1, "lineage_count": 0, "cum_total_count": 642, "cum_lineage_count": 0, "proportion": 0.0, "proportion_ci_lower": 7.645532637812184e-07, "proportion_ci_upper": 0.0039035214913949916}, {"date": "2021-06-17", "name": "Louisiana", "id": "USA_US-LA", "total_count": 1, "lineage_count": 0, "cum_total_count": 657, "cum_lineage_count": 2, "proportion": 0.0030441400304414, "proportion_ci_lower": 0.0006331039514082938, "proportion_ci_upper": 0.009729517424031275}, {"date": "2021-06-17", "name": "Maine", "id": "USA_US-ME", "total_count": 1, "lineage_count": 0, "cum_total_count": 465, "cum_lineage_count": 8, "proportion": 0.017204301075268817, "proportion_ci_lower": 0.008166293260293696, "proportion_ci_upper": 0.03219877955710837}, {"date": "2021-06-21", "name": "Maryland", "id": "USA_US-MD", "total_count": 2, "lineage_count": 0, "cum_total_count": 1431, "cum_lineage_count": 1, "proportion": 0.0006988120195667365, "proportion_ci_lower": 7.541050205615903e-05, "proportion_ci_upper": 0.003261628682230455}, {"date": "2021-06-11", "name": "Massachusetts", "id": "USA_US-MA", "total_count": 2, "lineage_count": 0, "cum_total_count": 3094, "cum_lineage_count": 11, "proportion": 0.003555268261150614, "proportion_ci_lower": 0.0018903295272500252, "proportion_ci_upper": 0.006144650952329633}, {"date": "2021-06-12", "name": "Michigan", "id": "USA_US-MI", "total_count": 1, "lineage_count": 0, "cum_total_count": 1350, "cum_lineage_count": 7, "proportion": 0.005185185185185185, "proportion_ci_lower": 0.0023222108182672572, "proportion_ci_upper": 0.010153589533418272}, {"date": "2021-06-24", "name": "Minnesota", "id": "USA_US-MN", "total_count": 1, "lineage_count": 0, "cum_total_count": 4455, "cum_lineage_count": 85, "proportion": 0.019079685746352413, "proportion_ci_lower": 0.015368477799189827, "proportion_ci_upper": 0.023415226043317028}, {"date": "2021-06-16", "name": "Mississippi", "id": "USA_US-MS", "total_count": 1, "lineage_count": 0, "cum_total_count": 247, "cum_lineage_count": 0, "proportion": 0.0, "proportion_ci_lower": 1.9859810714029892e-06, "proportion_ci_upper": 0.010108079755384832}, {"date": "2021-06-23", "name": "Missouri", "id": "USA_US-MO", "total_count": 1, "lineage_count": 0, "cum_total_count": 844, "cum_lineage_count": 1, "proportion": 0.001184834123222749, "proportion_ci_lower": 0.00012787051962671544, "proportion_ci_upper": 0.005524479518626446}, {"date": "2021-06-26", "name": "Montana", "id": "USA_US-MT", "total_count": 2, "lineage_count": 0, "cum_total_count": 450, "cum_lineage_count": 1, "proportion": 0.0022222222222222222, "proportion_ci_lower": 0.00023987710658222554, "proportion_ci_upper": 0.010339077080917525}, {"date": "2021-06-25", "name": "Nebraska", "id": "USA_US-NE", "total_count": 5, "lineage_count": 0, "cum_total_count": 529, "cum_lineage_count": 5, "proportion": 0.00945179584120983, "proportion_ci_lower": 0.003615441785855391, "proportion_ci_upper": 0.020592151945530768}, {"date": "2021-06-22", "name": "Nevada", "id": "USA_US-NV", "total_count": 2, "lineage_count": 0, "cum_total_count": 376, "cum_lineage_count": 6, "proportion": 0.015957446808510637, "proportion_ci_lower": 0.006687295966157418, "proportion_ci_upper": 0.0325935212389773}, {"date": "2021-06-06", "name": "New Hampshire", "id": "USA_US-NH", "total_count": 4, "lineage_count": 0, "cum_total_count": 405, "cum_lineage_count": 1, "proportion": 0.0024691358024691358, "proportion_ci_lower": 0.0002665430432844057, "proportion_ci_upper": 0.011481951608994456}, {"date": "2021-06-21", "name": "New Jersey", "id": "USA_US-NJ", "total_count": 1, "lineage_count": 0, "cum_total_count": 1379, "cum_lineage_count": 3, "proportion": 0.002175489485134155, "proportion_ci_lower": 0.0006130835085379379, "proportion_ci_upper": 0.005794352567429661}, {"date": "2021-06-12", "name": "New Mexico", "id": "USA_US-NM", "total_count": 1, "lineage_count": 0, "cum_total_count": 669, "cum_lineage_count": 16, "proportion": 0.02391629297458894, "proportion_ci_lower": 0.014299366251331283, "proportion_ci_upper": 0.03763152987742069}, {"date": "2021-06-19", "name": "New York", "id": "USA_US-NY", "total_count": 3, "lineage_count": 0, "cum_total_count": 2933, "cum_lineage_count": 7, "proportion": 0.002386634844868735, "proportion_ci_lower": 0.001068144903318947, "proportion_ci_upper": 0.0046802688423820404}, {"date": "2021-06-11", "name": "North Carolina", "id": "USA_US-NC", "total_count": 2, "lineage_count": 0, "cum_total_count": 1736, "cum_lineage_count": 2, "proportion": 0.001152073732718894, "proportion_ci_lower": 0.00023947908029574736, "proportion_ci_upper": 0.003690767654535243}, {"date": "2021-06-11", "name": "North Dakota", "id": "USA_US-ND", "total_count": 1, "lineage_count": 0, "cum_total_count": 640, "cum_lineage_count": 13, "proportion": 0.0203125, "proportion_ci_lower": 0.011432212611579898, "proportion_ci_upper": 0.033505919443534316}, {"date": "2021-06-15", "name": "Ohio", "id": "USA_US-OH", "total_count": 108, "lineage_count": 0, "cum_total_count": 1907, "cum_lineage_count": 1, "proportion": 0.0005243838489774515, "proportion_ci_lower": 5.658559862033964e-05, "proportion_ci_upper": 0.002448395180127738}, {"date": "2021-06-09", "name": "Oklahoma", "id": "USA_US-OK", "total_count": 1, "lineage_count": 0, "cum_total_count": 105, "cum_lineage_count": 0, "proportion": 0.0, "proportion_ci_lower": 4.66538743475149e-06, "proportion_ci_upper": 0.02358371562193458}, {"date": "2021-06-23", "name": "Oregon", "id": "USA_US-OR", "total_count": 1, "lineage_count": 0, "cum_total_count": 1252, "cum_lineage_count": 33, "proportion": 0.026357827476038338, "proportion_ci_lower": 0.01854464544276294, "proportion_ci_upper": 0.036355202940699716}, {"date": "2021-06-15", "name": "Pennsylvania", "id": "USA_US-PA", "total_count": 1, "lineage_count": 0, "cum_total_count": 1859, "cum_lineage_count": 3, "proportion": 0.0016137708445400753, "proportion_ci_lower": 0.0004547127497174171, "proportion_ci_upper": 0.004300448000165491}, {"date": "2021-06-08", "name": "Rhode Island", "id": "USA_US-RI", "total_count": 1, "lineage_count": 0, "cum_total_count": 782, "cum_lineage_count": 0, "proportion": 0.0, "proportion_ci_lower": 6.277205233453726e-07, "proportion_ci_upper": 0.003206026102235909}, {"date": "2021-06-10", "name": "South Carolina", "id": "USA_US-SC", "total_count": 1, "lineage_count": 0, "cum_total_count": 443, "cum_lineage_count": 0, "proportion": 0.0, "proportion_ci_lower": 1.1078041928364996e-06, "proportion_ci_upper": 0.005651072167893554}, {"date": "2021-06-08", "name": "South Dakota", "id": "USA_US-SD", "total_count": 2, "lineage_count": 0, "cum_total_count": 48, "cum_lineage_count": 0, "proportion": 0.0, "proportion_ci_lower": 1.0176693619626449e-05, "proportion_ci_upper": 0.05072726335249247}, {"date": "2021-06-12", "name": "Tennessee", "id": "USA_US-TN", "total_count": 1, "lineage_count": 0, "cum_total_count": 656, "cum_lineage_count": 0, "proportion": 0.0, "proportion_ci_lower": 7.482428026494124e-07, "proportion_ci_upper": 0.0038204056764127177}, {"date": "2021-06-16", "name": "Texas", "id": "USA_US-TX", "total_count": 2, "lineage_count": 0, "cum_total_count": 3255, "cum_lineage_count": 11, "proportion": 0.003379416282642089, "proportion_ci_lower": 0.0017967623470553909, "proportion_ci_upper": 0.005841121025082607}, {"date": "2021-06-14", "name": "Unknown", "id": "USA_US-None", "total_count": 1, "lineage_count": 0, "cum_total_count": 46, "cum_lineage_count": 0, "proportion": 0.0, "proportion_ci_lower": 1.0616751927119647e-05, "proportion_ci_upper": 0.05286170463923311}, {"date": "2021-06-11", "name": "Utah", "id": "USA_US-UT", "total_count": 1, "lineage_count": 0, "cum_total_count": 1031, "cum_lineage_count": 21, "proportion": 0.020368574199806012, "proportion_ci_lower": 0.01303512130649321, "proportion_ci_upper": 0.030385106858742517}, {"date": "2021-06-06", "name": "Vermont", "id": "USA_US-VT", "total_count": 1, "lineage_count": 0, "cum_total_count": 244, "cum_lineage_count": 1, "proportion": 0.004098360655737705, "proportion_ci_lower": 0.0004425594364555045, "proportion_ci_upper": 0.018993565938421386}, {"date": "2021-05-30", "name": "Virgin Islands", "id": "USA_US-None", "total_count": 1, "lineage_count": 0, "cum_total_count": 1, "cum_lineage_count": 0, "proportion": 0.0, "proportion_ci_lower": 0.00038558098075590136, "proportion_ci_upper": 0.8532536836904249}, {"date": "2021-05-26", "name": "Virgin Islands of the U.S.", "id": "USA_US-None", "total_count": 1, "lineage_count": 0, "cum_total_count": 9, "cum_lineage_count": 0, "proportion": 0.0, "proportion_ci_lower": 5.306405341849297e-05, "proportion_ci_upper": 0.23761009863290297}, {"date": "2021-06-10", "name": "Virginia", "id": "USA_US-VA", "total_count": 3, "lineage_count": 0, "cum_total_count": 1014, "cum_lineage_count": 1, "proportion": 0.0009861932938856016, "proportion_ci_lower": 0.00010642851316521272, "proportion_ci_upper": 0.004600190490028466}, {"date": "2021-06-22", "name": "Washington", "id": "USA_US-WA", "total_count": 5, "lineage_count": 0, "cum_total_count": 6067, "cum_lineage_count": 357, "proportion": 0.058842920718641833, "proportion_ci_lower": 0.053130651223744545, "proportion_ci_upper": 0.06497594654822214}, {"date": "2021-06-11", "name": "West Virginia", "id": "USA_US-WV", "total_count": 1, "lineage_count": 0, "cum_total_count": 1293, "cum_lineage_count": 1, "proportion": 0.0007733952049497294, "proportion_ci_lower": 8.346017573306555e-05, "proportion_ci_upper": 0.0036091758872370816}, {"date": "2021-06-17", "name": "Wisconsin", "id": "USA_US-WI", "total_count": 1, "lineage_count": 0, "cum_total_count": 1492, "cum_lineage_count": 11, "proportion": 0.007372654155495978, "proportion_ci_lower": 0.00392320530092531, "proportion_ci_upper": 0.012723430355716436}, {"date": "2021-06-25", "name": "Wyoming", "id": "USA_US-WY", "total_count": 2, "lineage_count": 0, "cum_total_count": 676, "cum_lineage_count": 6, "proportion": 0.008875739644970414, "proportion_ci_lower": 0.00371293831719024, "proportion_ci_upper": 0.01820277275120985}]}