{"success": true, "results": [{"date": "2021-03-15", "name": "Ae", "id": "USA_US-None", "total_count": 1, "lineage_count": 0, "cum_total_count": 1, "cum_lineage_count": 0, "proportion": 0.0, "proportion_ci_lower": 0.00038558098075590136, "proportion_ci_upper": 0.8532536836904249}, {"date": "2021-04-12", "name": "Alabama", "id": "USA_US-AL", "total_count": 4, "lineage_count": 0, "cum_total_count": 259, "cum_lineage_count": 8, "proportion": 0.03088803088803089, "proportion_ci_lower": 0.014708906951369343, "proportion_ci_upper": 0.0574318501565898}, {"date": "2021-04-15", "name": "Alaska", "id": "USA_US-AK", "total_count": 2, "lineage_count": 0, "cum_total_count": 418, "cum_lineage_count": 45, "proportion": 0.1076555023923445, "proportion_ci_lower": 0.08065886640796673, "proportion_ci_upper": 0.14006061115731105}, {"date": "2021-04-15", "name": "Arizona", "id": "USA_US-AZ", "total_count": 2, "lineage_count": 0, "cum_total_count": 1886, "cum_lineage_count": 479, "proportion": 0.2539766702014846, "proportion_ci_lower": 0.23471940507414157, "proportion_ci_upper": 0.2739883725149237}, {"date": "2021-04-08", "name": "Arkansas", "id": "USA_US-AR", "total_count": 2, "lineage_count": 1, "cum_total_count": 116, "cum_lineage_count": 3, "proportion": 0.02586206896551724, "proportion_ci_lower": 0.007336531068619992, "proportion_ci_upper": 0.06740037552419109}, {"date": "2021-04-13", "name": "California", "id": "USA_US-CA", "total_count": 113, "lineage_count": 14, "cum_total_count": 10843, "cum_lineage_count": 3455, "proportion": 0.3186387531126072, "proportion_ci_lower": 0.30991781772473637, "proportion_ci_upper": 0.32745649479321026}, {"date": "2021-04-13", "name": "Colorado", "id": "USA_US-CO", "total_count": 5, "lineage_count": 0, "cum_total_count": 3835, "cum_lineage_count": 507, "proportion": 0.13220338983050847, "proportion_ci_lower": 0.12176205737980499, "proportion_ci_upper": 0.14319961451278507}, {"date": "2021-04-12", "name": "Connecticut", "id": "USA_US-CT", "total_count": 1, "lineage_count": 0, "cum_total_count": 2198, "cum_lineage_count": 68, "proportion": 0.030937215650591446, "proportion_ci_lower": 0.024303788364195784, "proportion_ci_upper": 0.038804275752164386}, {"date": "2021-04-08", "name": "Delaware", "id": "USA_US-DE", "total_count": 1, "lineage_count": 0, "cum_total_count": 303, "cum_lineage_count": 5, "proportion": 0.0165016501650165, "proportion_ci_lower": 0.006323752069831045, "proportion_ci_upper": 0.03578755374635623}, {"date": "2021-04-13", "name": "District of Columbia", "id": "USA_US-DC", "total_count": 3, "lineage_count": 0, "cum_total_count": 173, "cum_lineage_count": 5, "proportion": 0.028901734104046242, "proportion_ci_lower": 0.01111190002710814, "proportion_ci_upper": 0.06217766976166228}, {"date": "2021-04-13", "name": "Florida", "id": "USA_US-FL", "total_count": 24, "lineage_count": 0, "cum_total_count": 9342, "cum_lineage_count": 374, "proportion": 0.04003425390708628, "proportion_ci_lower": 0.03620039474081502, "proportion_ci_upper": 0.044153042146145016}, {"date": "2021-03-10", "name": "GA", "id": "USA_US-None", "total_count": 1, "lineage_count": 0, "cum_total_count": 1, "cum_lineage_count": 0, "proportion": 0.0, "proportion_ci_lower": 0.00038558098075590136, "proportion_ci_upper": 0.8532536836904249}, {"date": "2021-04-13", "name": "Georgia", "id": "USA_US-GA", "total_count": 2, "lineage_count": 0, "cum_total_count": 1845, "cum_lineage_count": 75, "proportion": 0.04065040650406504, "proportion_ci_lower": 0.032347774763237365, "proportion_ci_upper": 0.050392173539906326}, {"date": "2021-04-12", "name": "Hawaii", "id": "USA_US-HI", "total_count": 1, "lineage_count": 0, "cum_total_count": 282, "cum_lineage_count": 191, "proportion": 0.6773049645390071, "proportion_ci_lower": 0.6211462634974908, "proportion_ci_upper": 0.729845257600039}, {"date": "2021-04-09", "name": "Idaho", "id": "USA_US-ID", "total_count": 1, "lineage_count": 0, "cum_total_count": 347, "cum_lineage_count": 25, "proportion": 0.07204610951008646, "proportion_ci_lower": 0.04834396933645993, "proportion_ci_upper": 0.10284366082350538}, {"date": "2021-04-14", "name": "Illinois", "id": "USA_US-IL", "total_count": 2, "lineage_count": 0, "cum_total_count": 3807, "cum_lineage_count": 240, "proportion": 0.06304176516942474, "proportion_ci_lower": 0.05565172939532482, "proportion_ci_upper": 0.0710958157204048}, {"date": "2021-04-12", "name": "Indiana", "id": "USA_US-IN", "total_count": 1, "lineage_count": 0, "cum_total_count": 1675, "cum_lineage_count": 83, "proportion": 0.04955223880597015, "proportion_ci_lower": 0.039926723691081446, "proportion_ci_upper": 0.060732197894973305}, {"date": "2021-04-12", "name": "Iowa", "id": "USA_US-IA", "total_count": 1, "lineage_count": 0, "cum_total_count": 242, "cum_lineage_count": 16, "proportion": 0.06611570247933884, "proportion_ci_lower": 0.03985167236858998, "proportion_ci_upper": 0.10266490626396052}, {"date": "2021-04-21", "name": "Kansas", "id": "USA_US-KS", "total_count": 1, "lineage_count": 0, "cum_total_count": 484, "cum_lineage_count": 26, "proportion": 0.05371900826446281, "proportion_ci_lower": 0.03623316776688132, "proportion_ci_upper": 0.07651649030325791}, {"date": "2021-04-07", "name": "Kentucky", "id": "USA_US-KY", "total_count": 2, "lineage_count": 0, "cum_total_count": 572, "cum_lineage_count": 11, "proportion": 0.019230769230769232, "proportion_ci_lower": 0.010259181253101546, "proportion_ci_upper": 0.03303467728863674}, {"date": "2021-04-12", "name": "Louisiana", "id": "USA_US-LA", "total_count": 3, "lineage_count": 1, "cum_total_count": 344, "cum_lineage_count": 22, "proportion": 0.06395348837209303, "proportion_ci_lower": 0.04167931509795286, "proportion_ci_upper": 0.09351817836383725}, {"date": "2021-04-09", "name": "Maine", "id": "USA_US-ME", "total_count": 2, "lineage_count": 0, "cum_total_count": 673, "cum_lineage_count": 54, "proportion": 0.08023774145616643, "proportion_ci_lower": 0.06150279760594313, "proportion_ci_upper": 0.1025720898988921}, {"date": "2021-04-19", "name": "Maryland", "id": "USA_US-MD", "total_count": 2, "lineage_count": 0, "cum_total_count": 3518, "cum_lineage_count": 41, "proportion": 0.011654349061967027, "proportion_ci_lower": 0.008496661455302939, "proportion_ci_upper": 0.01561431797287649}, {"date": "2021-04-13", "name": "Massachusetts", "id": "USA_US-MA", "total_count": 3, "lineage_count": 0, "cum_total_count": 3896, "cum_lineage_count": 93, "proportion": 0.023870636550308008, "proportion_ci_lower": 0.019424567883661363, "proportion_ci_upper": 0.02902350498994688}, {"date": "2021-04-13", "name": "Michigan", "id": "USA_US-MI", "total_count": 5, "lineage_count": 0, "cum_total_count": 6516, "cum_lineage_count": 220, "proportion": 0.03376304481276857, "proportion_ci_lower": 0.02958244165185467, "proportion_ci_upper": 0.038357656016084096}, {"date": "2021-04-16", "name": "Minnesota", "id": "USA_US-MN", "total_count": 1, "lineage_count": 0, "cum_total_count": 5359, "cum_lineage_count": 425, "proportion": 0.0793058406419108, "proportion_ci_lower": 0.07229783981775131, "proportion_ci_upper": 0.08676808548778592}, {"date": "2021-04-13", "name": "Mississippi", "id": "USA_US-MS", "total_count": 3, "lineage_count": 0, "cum_total_count": 298, "cum_lineage_count": 19, "proportion": 0.06375838926174497, "proportion_ci_lower": 0.04014410778341539, "proportion_ci_upper": 0.09578394172142435}, {"date": "2021-04-12", "name": "Missouri", "id": "USA_US-MO", "total_count": 2, "lineage_count": 0, "cum_total_count": 503, "cum_lineage_count": 24, "proportion": 0.04771371769383698, "proportion_ci_lower": 0.03161190163639831, "proportion_ci_upper": 0.06899513759895304}, {"date": "2021-04-05", "name": "Montana", "id": "USA_US-MT", "total_count": 10, "lineage_count": 0, "cum_total_count": 202, "cum_lineage_count": 22, "proportion": 0.10891089108910891, "proportion_ci_lower": 0.07154042773374834, "proportion_ci_upper": 0.15738312884904693}, {"date": "2021-04-12", "name": "Nebraska", "id": "USA_US-NE", "total_count": 9, "lineage_count": 0, "cum_total_count": 307, "cum_lineage_count": 16, "proportion": 0.05211726384364821, "proportion_ci_lower": 0.03132895187162715, "proportion_ci_upper": 0.08128552615601603}, {"date": "2021-04-19", "name": "Nevada", "id": "USA_US-NV", "total_count": 5, "lineage_count": 0, "cum_total_count": 552, "cum_lineage_count": 197, "proportion": 0.35688405797101447, "proportion_ci_lower": 0.31774986132417443, "proportion_ci_upper": 0.3975146251908792}, {"date": "2021-04-11", "name": "New Hampshire", "id": "USA_US-NH", "total_count": 1, "lineage_count": 0, "cum_total_count": 581, "cum_lineage_count": 37, "proportion": 0.06368330464716007, "proportion_ci_lower": 0.045963435906709565, "proportion_ci_upper": 0.0857337376992644}, {"date": "2021-04-13", "name": "New Jersey", "id": "USA_US-NJ", "total_count": 2, "lineage_count": 0, "cum_total_count": 5301, "cum_lineage_count": 50, "proportion": 0.009432182607055273, "proportion_ci_lower": 0.007090023867763107, "proportion_ci_upper": 0.012309382255855872}, {"date": "2021-04-12", "name": "New Mexico", "id": "USA_US-NM", "total_count": 1, "lineage_count": 0, "cum_total_count": 583, "cum_lineage_count": 91, "proportion": 0.15608919382504288, "proportion_ci_lower": 0.12836188313835895, "proportion_ci_upper": 0.18722076234225715}, {"date": "2021-04-15", "name": "New York", "id": "USA_US-NY", "total_count": 34, "lineage_count": 0, "cum_total_count": 14094, "cum_lineage_count": 161, "proportion": 0.011423300695331347, "proportion_ci_lower": 0.009767622684828944, "proportion_ci_upper": 0.013279564694320567}, {"date": "2021-04-13", "name": "North Carolina", "id": "USA_US-NC", "total_count": 4, "lineage_count": 0, "cum_total_count": 2130, "cum_lineage_count": 98, "proportion": 0.046009389671361506, "proportion_ci_lower": 0.03772067976894859, "proportion_ci_upper": 0.05553044422074427}, {"date": "2021-04-08", "name": "North Dakota", "id": "USA_US-ND", "total_count": 3, "lineage_count": 1, "cum_total_count": 261, "cum_lineage_count": 54, "proportion": 0.20689655172413793, "proportion_ci_lower": 0.16114481821226323, "proportion_ci_upper": 0.2591063748095189}, {"date": "2021-03-18", "name": "North Dalota", "id": "USA_US-None", "total_count": 1, "lineage_count": 1, "cum_total_count": 1, "cum_lineage_count": 1, "proportion": 1.0, "proportion_ci_lower": 0.14674631630957516, "proportion_ci_upper": 0.9996144190192441}, {"date": "2021-04-15", "name": "Ohio", "id": "USA_US-OH", "total_count": 85, "lineage_count": 0, "cum_total_count": 2473, "cum_lineage_count": 142, "proportion": 0.05742013748483623, "proportion_ci_lower": 0.04876430158250667, "proportion_ci_upper": 0.06711096927258464}, {"date": "2021-04-13", "name": "Oklahoma", "id": "USA_US-OK", "total_count": 1, "lineage_count": 0, "cum_total_count": 124, "cum_lineage_count": 1, "proportion": 0.008064516129032258, "proportion_ci_lower": 0.0008715232279750089, "proportion_ci_upper": 0.037067243124749516}, {"date": "2021-04-09", "name": "Oregon", "id": "USA_US-OR", "total_count": 3, "lineage_count": 0, "cum_total_count": 666, "cum_lineage_count": 189, "proportion": 0.28378378378378377, "proportion_ci_lower": 0.25053607533135963, "proportion_ci_upper": 0.3189060841137984}, {"date": "2021-04-15", "name": "Pennsylvania", "id": "USA_US-PA", "total_count": 1, "lineage_count": 0, "cum_total_count": 4709, "cum_lineage_count": 136, "proportion": 0.02888086642599278, "proportion_ci_lower": 0.02438297955889067, "proportion_ci_upper": 0.03395750217562832}, {"date": "2021-04-07", "name": "Puerto Rico", "id": "USA_US-None", "total_count": 2, "lineage_count": 0, "cum_total_count": 207, "cum_lineage_count": 4, "proportion": 0.01932367149758454, "proportion_ci_lower": 0.006556858916241899, "proportion_ci_upper": 0.04528545611832757}, {"date": "2021-04-10", "name": "Rhode Island", "id": "USA_US-RI", "total_count": 5, "lineage_count": 0, "cum_total_count": 953, "cum_lineage_count": 43, "proportion": 0.04512067156348373, "proportion_ci_lower": 0.033293700351693455, "proportion_ci_upper": 0.05970333329732802}, {"date": "2021-04-10", "name": "South Carolina", "id": "USA_US-SC", "total_count": 1, "lineage_count": 0, "cum_total_count": 350, "cum_lineage_count": 31, "proportion": 0.08857142857142856, "proportion_ci_lower": 0.06217515326112769, "proportion_ci_upper": 0.12173333544735876}, {"date": "2021-04-06", "name": "South Dakota", "id": "USA_US-SD", "total_count": 2, "lineage_count": 0, "cum_total_count": 167, "cum_lineage_count": 16, "proportion": 0.09580838323353294, "proportion_ci_lower": 0.05808697903505471, "proportion_ci_upper": 0.14737595872713327}, {"date": "2021-04-12", "name": "Tennessee", "id": "USA_US-TN", "total_count": 9, "lineage_count": 0, "cum_total_count": 1135, "cum_lineage_count": 20, "proportion": 0.01762114537444934, "proportion_ci_lower": 0.011141674804953369, "proportion_ci_upper": 0.026551856679762564}, {"date": "2021-04-17", "name": "Texas", "id": "USA_US-TX", "total_count": 6, "lineage_count": 0, "cum_total_count": 5584, "cum_lineage_count": 270, "proportion": 0.04835243553008596, "proportion_ci_lower": 0.042958454855059114, "proportion_ci_upper": 0.05421440787934795}, {"date": "2021-04-10", "name": "Unknown", "id": "USA_US-None", "total_count": 12, "lineage_count": 4, "cum_total_count": 41, "cum_lineage_count": 9, "proportion": 0.21951219512195122, "proportion_ci_lower": 0.11454702457008827, "proportion_ci_upper": 0.36247575043612146}, {"date": "2021-04-13", "name": "Utah", "id": "USA_US-UT", "total_count": 1, "lineage_count": 1, "cum_total_count": 361, "cum_lineage_count": 76, "proportion": 0.21052631578947367, "proportion_ci_lower": 0.17088381294221042, "proportion_ci_upper": 0.25478857579241376}, {"date": "2021-04-10", "name": "Vermont", "id": "USA_US-VT", "total_count": 1, "lineage_count": 0, "cum_total_count": 295, "cum_lineage_count": 28, "proportion": 0.09491525423728814, "proportion_ci_lower": 0.0654131003142093, "proportion_ci_upper": 0.13231315290195034}, {"date": "2021-04-16", "name": "Virginia", "id": "USA_US-VA", "total_count": 6, "lineage_count": 0, "cum_total_count": 1539, "cum_lineage_count": 53, "proportion": 0.03443794671864847, "proportion_ci_lower": 0.026183595413928826, "proportion_ci_upper": 0.044440178981873024}, {"date": "2021-04-14", "name": "Washington", "id": "USA_US-WA", "total_count": 41, "lineage_count": 1, "cum_total_count": 4831, "cum_lineage_count": 1401, "proportion": 0.2900020699648106, "proportion_ci_lower": 0.277335134550745, "proportion_ci_upper": 0.3029205433197423}, {"date": "2021-04-13", "name": "West Virginia", "id": "USA_US-WV", "total_count": 1, "lineage_count": 0, "cum_total_count": 1296, "cum_lineage_count": 142, "proportion": 0.1095679012345679, "proportion_ci_lower": 0.09343568944272364, "proportion_ci_upper": 0.1274414185291769}, {"date": "2021-04-13", "name": "Wisconsin", "id": "USA_US-WI", "total_count": 3, "lineage_count": 0, "cum_total_count": 2277, "cum_lineage_count": 186, "proportion": 0.08168642951251646, "proportion_ci_lower": 0.07096656967150093, "proportion_ci_upper": 0.09346877098715356}, {"date": "2021-04-12", "name": "Wyoming", "id": "USA_US-WY", "total_count": 1, "lineage_count": 0, "cum_total_count": 301, "cum_lineage_count": 48, "proportion": 0.15946843853820597, "proportion_ci_lower": 0.12145241591376427, "proportion_ci_upper": 0.20399475391130673}]}