{"success": true, "results": [{"date": "2021-07-09", "name": "Alabama", "id": "USA_US-AL", "total_count": 18, "lineage_count": 0, "cum_total_count": 244, "cum_lineage_count": 1, "proportion": 0.004098360655737705, "proportion_ci_lower": 0.0004425594364555045, "proportion_ci_upper": 0.018993565938421386}, {"date": "2021-06-27", "name": "Alaska", "id": "USA_US-AK", "total_count": 1, "lineage_count": 0, "cum_total_count": 434, "cum_lineage_count": 7, "proportion": 0.016129032258064516, "proportion_ci_lower": 0.007242645423868725, "proportion_ci_upper": 0.03140492219990154}, {"date": "2021-07-01", "name": "Arizona", "id": "USA_US-AZ", "total_count": 8, "lineage_count": 0, "cum_total_count": 1008, "cum_lineage_count": 2, "proportion": 0.001984126984126984, "proportion_ci_lower": 0.0004125293385788517, "proportion_ci_upper": 0.0063498259994154704}, {"date": "2021-06-28", "name": "Arkansas", "id": "USA_US-AR", "total_count": 3, "lineage_count": 0, "cum_total_count": 215, "cum_lineage_count": 0, "proportion": 0.0, "proportion_ci_lower": 2.2812249347804654e-06, "proportion_ci_upper": 0.011602036788265397}, {"date": "2021-07-01", "name": "California", "id": "USA_US-CA", "total_count": 11, "lineage_count": 0, "cum_total_count": 4834, "cum_lineage_count": 25, "proportion": 0.00517170045510964, "proportion_ci_lower": 0.003432871498148438, "proportion_ci_upper": 0.007501786189675674}, {"date": "2021-06-26", "name": "Colorado", "id": "USA_US-CO", "total_count": 5, "lineage_count": 0, "cum_total_count": 2646, "cum_lineage_count": 11, "proportion": 0.0041572184429327285, "proportion_ci_lower": 0.0022106675835731763, "proportion_ci_upper": 0.007183334849694689}, {"date": "2021-06-25", "name": "Connecticut", "id": "USA_US-CT", "total_count": 1, "lineage_count": 0, "cum_total_count": 384, "cum_lineage_count": 0, "proportion": 0.0, "proportion_ci_lower": 1.2779027739184436e-06, "proportion_ci_upper": 0.0065159373526723395}, {"date": "2021-06-25", "name": "Delaware", "id": "USA_US-DE", "total_count": 1, "lineage_count": 0, "cum_total_count": 228, "cum_lineage_count": 0, "proportion": 0.0, "proportion_ci_lower": 2.1512978566220456e-06, "proportion_ci_upper": 0.010944873700535764}, {"date": "2021-06-30", "name": "District of Columbia", "id": "USA_US-DC", "total_count": 1, "lineage_count": 0, "cum_total_count": 132, "cum_lineage_count": 0, "proportion": 0.0, "proportion_ci_lower": 3.712913190019933e-06, "proportion_ci_upper": 0.01881456214017113}, {"date": "2021-06-30", "name": "Florida", "id": "USA_US-FL", "total_count": 2, "lineage_count": 0, "cum_total_count": 3654, "cum_lineage_count": 6, "proportion": 0.0016420361247947454, "proportion_ci_lower": 0.0006856602568989706, "proportion_ci_upper": 0.0033815497936218186}, {"date": "2021-06-28", "name": "Georgia", "id": "USA_US-GA", "total_count": 1, "lineage_count": 0, "cum_total_count": 522, "cum_lineage_count": 1, "proportion": 0.0019157088122605363, "proportion_ci_lower": 0.00020677816391315886, "proportion_ci_upper": 0.008918695435848223}, {"date": "2021-05-28", "name": "Guam", "id": "USA_US-None", "total_count": 1, "lineage_count": 0, "cum_total_count": 10, "cum_lineage_count": 0, "proportion": 0.0, "proportion_ci_lower": 4.789043315758197e-05, "proportion_ci_upper": 0.21719626750921056}, {"date": "2021-06-28", "name": "Hawaii", "id": "USA_US-HI", "total_count": 1, "lineage_count": 0, "cum_total_count": 297, "cum_lineage_count": 25, "proportion": 0.08417508417508418, "proportion_ci_lower": 0.056596564820499566, "proportion_ci_upper": 0.11980278714917292}, {"date": "2021-06-24", "name": "Idaho", "id": "USA_US-ID", "total_count": 2, "lineage_count": 0, "cum_total_count": 198, "cum_lineage_count": 3, "proportion": 0.015151515151515152, "proportion_ci_lower": 0.004285311397083656, "proportion_ci_upper": 0.03987763999886951}, {"date": "2021-07-06", "name": "Illinois", "id": "USA_US-IL", "total_count": 5, "lineage_count": 0, "cum_total_count": 1561, "cum_lineage_count": 1, "proportion": 0.0006406149903907751, "proportion_ci_lower": 6.912953017386838e-05, "proportion_ci_upper": 0.002990363491283232}, {"date": "2021-07-06", "name": "Indiana", "id": "USA_US-IN", "total_count": 1, "lineage_count": 0, "cum_total_count": 923, "cum_lineage_count": 3, "proportion": 0.0032502708559046588, "proportion_ci_lower": 0.0009162441024922927, "proportion_ci_upper": 0.008648465181726128}, {"date": "2021-06-27", "name": "Iowa", "id": "USA_US-IA", "total_count": 2, "lineage_count": 0, "cum_total_count": 78, "cum_lineage_count": 0, "proportion": 0.0, "proportion_ci_lower": 6.275150301788441e-06, "proportion_ci_upper": 0.031591300912841735}, {"date": "2021-07-07", "name": "Kansas", "id": "USA_US-KS", "total_count": 21, "lineage_count": 0, "cum_total_count": 1121, "cum_lineage_count": 3, "proportion": 0.0026761819803746653, "proportion_ci_lower": 0.0007542900312062652, "proportion_ci_upper": 0.00712465735473522}, {"date": "2021-06-26", "name": "Kentucky", "id": "USA_US-KY", "total_count": 3, "lineage_count": 0, "cum_total_count": 302, "cum_lineage_count": 0, "proportion": 0.0, "proportion_ci_lower": 1.6245955060305428e-06, "proportion_ci_upper": 0.008276365680337227}, {"date": "2021-05-19", "name": "Los Angeles", "id": "USA_US-None", "total_count": 1, "lineage_count": 0, "cum_total_count": 4, "cum_lineage_count": 0, "proportion": 0.0, "proportion_ci_lower": 0.000115332788238275, "proportion_ci_upper": 0.4447626176576397}, {"date": "2021-06-28", "name": "Louisiana", "id": "USA_US-LA", "total_count": 1, "lineage_count": 0, "cum_total_count": 549, "cum_lineage_count": 1, "proportion": 0.0018214936247723133, "proportion_ci_lower": 0.00019660510946010144, "proportion_ci_upper": 0.00848173721268397}, {"date": "2021-06-21", "name": "Maine", "id": "USA_US-ME", "total_count": 1, "lineage_count": 0, "cum_total_count": 353, "cum_lineage_count": 2, "proportion": 0.0056657223796034, "proportion_ci_lower": 0.0011791669083836608, "proportion_ci_upper": 0.018050246984039342}, {"date": "2021-06-28", "name": "Maryland", "id": "USA_US-MD", "total_count": 4, "lineage_count": 0, "cum_total_count": 680, "cum_lineage_count": 1, "proportion": 0.0014705882352941176, "proportion_ci_lower": 0.00015871878055234443, "proportion_ci_upper": 0.006852768433859846}, {"date": "2021-06-27", "name": "Massachusetts", "id": "USA_US-MA", "total_count": 1, "lineage_count": 0, "cum_total_count": 905, "cum_lineage_count": 0, "proportion": 0.0, "proportion_ci_lower": 5.424296124606813e-07, "proportion_ci_upper": 0.0027710145405414406}, {"date": "2021-06-26", "name": "Michigan", "id": "USA_US-MI", "total_count": 1, "lineage_count": 0, "cum_total_count": 340, "cum_lineage_count": 0, "proportion": 0.0, "proportion_ci_lower": 1.4431567132354595e-06, "proportion_ci_upper": 0.007355449476765426}, {"date": "2021-07-06", "name": "Minnesota", "id": "USA_US-MN", "total_count": 1, "lineage_count": 0, "cum_total_count": 1911, "cum_lineage_count": 14, "proportion": 0.007326007326007326, "proportion_ci_lower": 0.004204639716458012, "proportion_ci_upper": 0.011933620631594533}, {"date": "2021-06-30", "name": "Mississippi", "id": "USA_US-MS", "total_count": 1, "lineage_count": 0, "cum_total_count": 320, "cum_lineage_count": 0, "proportion": 0.0, "proportion_ci_lower": 1.5332834737649884e-06, "proportion_ci_upper": 0.007813006440385893}, {"date": "2021-06-27", "name": "Missouri", "id": "USA_US-MO", "total_count": 3, "lineage_count": 0, "cum_total_count": 990, "cum_lineage_count": 0, "proportion": 0.0, "proportion_ci_lower": 4.958691453556609e-07, "proportion_ci_upper": 0.0025334608228716866}, {"date": "2021-06-26", "name": "Montana", "id": "USA_US-MT", "total_count": 2, "lineage_count": 0, "cum_total_count": 314, "cum_lineage_count": 0, "proportion": 0.0, "proportion_ci_lower": 1.562558534657772e-06, "proportion_ci_upper": 0.007961585138982605}, {"date": "2021-07-01", "name": "Nebraska", "id": "USA_US-NE", "total_count": 3, "lineage_count": 0, "cum_total_count": 297, "cum_lineage_count": 2, "proportion": 0.006734006734006734, "proportion_ci_lower": 0.001401909117066053, "proportion_ci_upper": 0.021425525500858522}, {"date": "2021-06-30", "name": "Nevada", "id": "USA_US-NV", "total_count": 3, "lineage_count": 0, "cum_total_count": 1164, "cum_lineage_count": 1, "proportion": 0.000859106529209622, "proportion_ci_lower": 9.271118702806816e-05, "proportion_ci_upper": 0.004008445031471464}, {"date": "2021-06-26", "name": "New Hampshire", "id": "USA_US-NH", "total_count": 1, "lineage_count": 0, "cum_total_count": 151, "cum_lineage_count": 1, "proportion": 0.006622516556291391, "proportion_ci_lower": 0.0007154845441100545, "proportion_ci_upper": 0.030530745656964897}, {"date": "2021-06-28", "name": "New Jersey", "id": "USA_US-NJ", "total_count": 2, "lineage_count": 0, "cum_total_count": 1088, "cum_lineage_count": 1, "proportion": 0.0009191176470588235, "proportion_ci_lower": 9.91885038611546e-05, "proportion_ci_upper": 0.004287909847246363}, {"date": "2021-06-29", "name": "New Mexico", "id": "USA_US-NM", "total_count": 7, "lineage_count": 0, "cum_total_count": 435, "cum_lineage_count": 1, "proportion": 0.0022988505747126436, "proportion_ci_lower": 0.0002481524651805728, "proportion_ci_upper": 0.010693888436423715}, {"date": "2021-07-06", "name": "New York", "id": "USA_US-NY", "total_count": 9, "lineage_count": 0, "cum_total_count": 1764, "cum_lineage_count": 8, "proportion": 0.0045351473922902496, "proportion_ci_lower": 0.002146307663389362, "proportion_ci_upper": 0.008539127118682543}, {"date": "2021-07-01", "name": "North Carolina", "id": "USA_US-NC", "total_count": 2, "lineage_count": 0, "cum_total_count": 1117, "cum_lineage_count": 0, "proportion": 0.0, "proportion_ci_lower": 4.3950274189807995e-07, "proportion_ci_upper": 0.0022458010351179827}, {"date": "2021-06-30", "name": "North Dakota", "id": "USA_US-ND", "total_count": 1, "lineage_count": 0, "cum_total_count": 428, "cum_lineage_count": 3, "proportion": 0.007009345794392523, "proportion_ci_lower": 0.001977976016420301, "proportion_ci_upper": 0.018586527936672814}, {"date": "2021-06-29", "name": "Ohio", "id": "USA_US-OH", "total_count": 1, "lineage_count": 0, "cum_total_count": 917, "cum_lineage_count": 1, "proportion": 0.0010905125408942203, "proportion_ci_lower": 0.00011768889990166888, "proportion_ci_upper": 0.005085690492829031}, {"date": "2021-06-27", "name": "Oklahoma", "id": "USA_US-OK", "total_count": 1, "lineage_count": 0, "cum_total_count": 88, "cum_lineage_count": 0, "proportion": 0.0, "proportion_ci_lower": 5.564093162696877e-06, "proportion_ci_upper": 0.028062365813494212}, {"date": "2021-07-05", "name": "Oregon", "id": "USA_US-OR", "total_count": 1, "lineage_count": 0, "cum_total_count": 884, "cum_lineage_count": 13, "proportion": 0.014705882352941176, "proportion_ci_lower": 0.008267315159678384, "proportion_ci_upper": 0.0243055912331106}, {"date": "2021-06-27", "name": "Pennsylvania", "id": "USA_US-PA", "total_count": 1, "lineage_count": 0, "cum_total_count": 666, "cum_lineage_count": 0, "proportion": 0.0, "proportion_ci_lower": 7.370121471798992e-07, "proportion_ci_upper": 0.003763171804665945}, {"date": "2021-06-26", "name": "Rhode Island", "id": "USA_US-RI", "total_count": 1, "lineage_count": 0, "cum_total_count": 343, "cum_lineage_count": 0, "proportion": 0.0, "proportion_ci_lower": 1.4305435603289816e-06, "proportion_ci_upper": 0.0072913979902976276}, {"date": "2021-06-28", "name": "South Carolina", "id": "USA_US-SC", "total_count": 3, "lineage_count": 0, "cum_total_count": 324, "cum_lineage_count": 0, "proportion": 0.0, "proportion_ci_lower": 1.5143686685804017e-06, "proportion_ci_upper": 0.007716996951632924}, {"date": "2021-06-18", "name": "South Dakota", "id": "USA_US-SD", "total_count": 1, "lineage_count": 0, "cum_total_count": 31, "cum_lineage_count": 0, "proportion": 0.0, "proportion_ci_lower": 1.5712479537001282e-05, "proportion_ci_upper": 0.07723003565348177}, {"date": "2021-06-28", "name": "Tennessee", "id": "USA_US-TN", "total_count": 3, "lineage_count": 0, "cum_total_count": 332, "cum_lineage_count": 0, "proportion": 0.0, "proportion_ci_lower": 1.4779053624852932e-06, "proportion_ci_upper": 0.007531886962188498}, {"date": "2021-07-07", "name": "Texas", "id": "USA_US-TX", "total_count": 10, "lineage_count": 0, "cum_total_count": 2613, "cum_lineage_count": 6, "proportion": 0.002296211251435132, "proportion_ci_lower": 0.0009589790573617255, "proportion_ci_upper": 0.004726963520182981}, {"date": "2021-06-14", "name": "Unknown", "id": "USA_US-None", "total_count": 2, "lineage_count": 0, "cum_total_count": 40, "cum_lineage_count": 0, "proportion": 0.0, "proportion_ci_lower": 1.219930657518636e-05, "proportion_ci_upper": 0.060497975214079645}, {"date": "2021-06-29", "name": "Utah", "id": "USA_US-UT", "total_count": 8, "lineage_count": 0, "cum_total_count": 2288, "cum_lineage_count": 9, "proportion": 0.003933566433566434, "proportion_ci_lower": 0.001948078248956382, "proportion_ci_upper": 0.007166835681988504}, {"date": "2021-06-06", "name": "Vermont", "id": "USA_US-VT", "total_count": 1, "lineage_count": 0, "cum_total_count": 36, "cum_lineage_count": 0, "proportion": 0.0, "proportion_ci_lower": 1.3545366988825864e-05, "proportion_ci_upper": 0.06694448234237448}, {"date": "2021-05-30", "name": "Virgin Islands", "id": "USA_US-None", "total_count": 1, "lineage_count": 0, "cum_total_count": 1, "cum_lineage_count": 0, "proportion": 0.0, "proportion_ci_lower": 0.00038558098075590136, "proportion_ci_upper": 0.8532536836904249}, {"date": "2021-05-26", "name": "Virgin Islands of the U.S.", "id": "USA_US-None", "total_count": 1, "lineage_count": 0, "cum_total_count": 5, "cum_lineage_count": 0, "proportion": 0.0, "proportion_ci_lower": 9.34206000395449e-05, "proportion_ci_upper": 0.37937714229903935}, {"date": "2021-06-29", "name": "Virginia", "id": "USA_US-VA", "total_count": 5, "lineage_count": 0, "cum_total_count": 717, "cum_lineage_count": 0, "proportion": 0.0, "proportion_ci_lower": 6.846069859432899e-07, "proportion_ci_upper": 0.003496060189814152}, {"date": "2021-07-07", "name": "Washington", "id": "USA_US-WA", "total_count": 4, "lineage_count": 0, "cum_total_count": 3919, "cum_lineage_count": 110, "proportion": 0.028068384792038787, "proportion_ci_lower": 0.02324009593639153, "proportion_ci_upper": 0.03359318632109698}, {"date": "2021-06-25", "name": "West Virginia", "id": "USA_US-WV", "total_count": 5, "lineage_count": 0, "cum_total_count": 682, "cum_lineage_count": 0, "proportion": 0.0, "proportion_ci_lower": 7.197278840656444e-07, "proportion_ci_upper": 0.0036750810022854507}, {"date": "2021-06-29", "name": "Wisconsin", "id": "USA_US-WI", "total_count": 1, "lineage_count": 0, "cum_total_count": 698, "cum_lineage_count": 4, "proportion": 0.0057306590257879654, "proportion_ci_lower": 0.0019373633007405998, "proportion_ci_upper": 0.013568049099922819}, {"date": "2021-06-26", "name": "Wyoming", "id": "USA_US-WY", "total_count": 1, "lineage_count": 0, "cum_total_count": 643, "cum_lineage_count": 0, "proportion": 0.0, "proportion_ci_lower": 7.633646856915161e-07, "proportion_ci_upper": 0.003897464898953836}]}